unittestreport/__init__.py
unittestreport/core/__init__.py
unittestreport/core/dataDriver.py
unittestreport/core/parameterized.py
unittestreport/core/reRun.py
unittestreport/core/resultPush.py
unittestreport/core/sendEmail.py
unittestreport/core/testResult.py
unittestreport/core/testRunner.py
unittestreport/templates/__init__.py
unittestreport/templates/dingtalk.md
unittestreport/templates/templates.html
unittestreport/templates/templates03.html
unittestreport/templates/templates2.html
unittestreport/templates/templates3.html
unittestreport-1.5.6.dist-info/LICENSE
unittestreport-1.5.6.dist-info/METADATA
unittestreport-1.5.6.dist-info/WHEEL
unittestreport-1.5.6.dist-info/top_level.txt
unittestreport-1.5.6.dist-info/RECORD
