Metadata-Version: 2.1
Name: unittestreport
Version: 1.5.6
Summary: A unittest report plugin for python3
Home-page: https://github.com/musen123/UnitTestReport
Author: MuSen
Author-email: musen_nmb@qq.com
Classifier: Programming Language :: Python :: 3
Requires-Python: >=3.7
License-File: LICENSE
Requires-Dist: Jinja2 (>=3.0.3)
Requires-Dist: PyYAML (>=5.3.1)
Requires-Dist: requests (>=2.24.0)
